.gitignore
CHANGELOG.md
LICENSE
PKG-INFO
README.md
pyproject.toml
.git_hooks/pre-commit
.github/ISSUE_TEMPLATE/bug_report.yml
.github/ISSUE_TEMPLATE/documentation_update.md
.github/ISSUE_TEMPLATE/feature_request.md
.github/PULL_REQUEST_TEMPLATE/pull_request_template.md
.github/actions/ophyd_devices_install/action.yml
.github/workflows/add-issues.yml
.github/workflows/check_pr.yml
.github/workflows/child_repos.yml
.github/workflows/ci.yml
.github/workflows/formatter.yml
.github/workflows/pytest-matrix.yml
.github/workflows/pytest.yml
.github/workflows/semantic_release.yml
.github/workflows/sync-issues-pr.yml
.gitlab/issue_templates/bug_report_template.md
.gitlab/issue_templates/documentation_update_template.md
.gitlab/issue_templates/feature_request_template.md
.gitlab/merge_request_templates/default.md
ophyd_devices/__init__.py
ophyd_devices/configs/__init__.py
ophyd_devices/configs/delay_generator_example.yaml
ophyd_devices/configs/dxp_examples.yaml
ophyd_devices/configs/epics_examples.yaml
ophyd_devices/configs/ophyd_devices_simulation.yaml
ophyd_devices/configs/ophyd_simulation.yaml
ophyd_devices/configs/sls_devices.yaml
ophyd_devices/devices/SpmBase.py
ophyd_devices/devices/XbpmBase.py
ophyd_devices/devices/__init__.py
ophyd_devices/devices/delay_generator_645.py
ophyd_devices/devices/device_list.md
ophyd_devices/devices/dxp.py
ophyd_devices/devices/optics_shutter.py
ophyd_devices/devices/psi_motor.py
ophyd_devices/devices/simple_positioner.py
ophyd_devices/devices/sls_devices.py
ophyd_devices/devices/softpositioner.py
ophyd_devices/devices/undulator.py
ophyd_devices/devices/areadetector/__init__.py
ophyd_devices/devices/areadetector/cam.py
ophyd_devices/devices/areadetector/plugins.py
ophyd_devices/interfaces/__init__.py
ophyd_devices/interfaces/base_classes/__init__.py
ophyd_devices/interfaces/base_classes/bec_device_base.py
ophyd_devices/interfaces/base_classes/ophyd_rotation_base.py
ophyd_devices/interfaces/base_classes/psi_detector_base.py
ophyd_devices-1.32.8.dist-info/METADATA
ophyd_devices-1.32.8.dist-info/WHEEL
ophyd_devices-1.32.8.dist-info/entry_points.txt
ophyd_devices-1.32.8.dist-info/licenses/LICENSE
ophyd_devices-1.32.8.dist-info/RECORD
